{
  "items": [
    {
      "graphid": 0,
      "name": "Untitled Graph",
      "userid": 0,
      "description": "Graph created via the workspace",
      "created_at": "2024-11-16T19:56:39.293Z",
      "updated_at": "2024-11-16T19:56:39.293Z",
      "version": 1,
      "nodes": [
        {
          "nodeid": "0",
          "x": 256,
          "y": 170.671875
        },
        {
          "nodeid": "1",
          "x": 722,
          "y": 74.671875
        }
      ],
      "edges": [
        {
          "from_nodeid": "0",
          "to_nodeid": "1"
        }
      ]
    },
    {
      "graphid": 1,
      "name": "Untitled Graph",
      "userid": 1,
      "description": "Graph created via the workspace",
      "created_at": "2024-11-16T21:28:06.127Z",
      "updated_at": "2024-11-16T21:28:06.127Z",
      "version": 1,
      "nodes": [
        {
          "nodeid": "0",
          "x": 324,
          "y": 106.671875
        },
        {
          "nodeid": "1",
          "x": 610,
          "y": 49.671875
        }
      ],
      "edges": [
        {
          "from_nodeid": "0",
          "to_nodeid": "1"
        }
      ]
    },
    {
      "graphid": 2,
      "name": "Untitled Graph",
      "userid": 2,
      "description": "Graph created via the workspace",
      "created_at": "2024-11-16T21:31:10.494Z",
      "updated_at": "2024-11-16T21:31:10.494Z",
      "version": 1,
      "nodes": [
        {
          "nodeid": "0",
          "x": 225,
          "y": 106.671875
        },
        {
          "nodeid": "1",
          "x": 576,
          "y": 62.671875
        }
      ],
      "edges": [
        {
          "from_nodeid": "0",
          "to_nodeid": "1"
        }
      ]
    },
    {
      "graphid": 3,
      "name": "Untitled Graph",
      "userid": 3,
      "description": "Graph created via the workspace",
      "created_at": "2024-11-16T21:34:00.739Z",
      "updated_at": "2024-11-16T21:34:00.739Z",
      "version": 1,
      "nodes": [
        {
          "nodeid": "0",
          "x": 334,
          "y": 100.671875
        },
        {
          "nodeid": "1",
          "x": 702,
          "y": 56.671875
        }
      ],
      "edges": [
        {
          "from_nodeid": "0",
          "to_nodeid": "1"
        }
      ]
    },
    {
      "graphid": 4,
      "name": "Untitled Graph",
      "userid": 4,
      "description": "Graph created via the workspace",
      "created_at": "2024-11-16T22:43:52.639Z",
      "updated_at": "2024-11-16T22:43:52.639Z",
      "version": 1,
      "nodes": [
        {
          "nodeid": "0",
          "x": 241,
          "y": 90.671875
        },
        {
          "nodeid": "1",
          "x": 573,
          "y": 48.671875
        }
      ],
      "edges": [
        {
          "from_nodeid": "0",
          "to_nodeid": "1"
        }
      ]
    },
    {
      "graphid": 5,
      "name": "Untitled Graph",
      "userid": 5,
      "description": "Graph created via the workspace",
      "created_at": "2024-11-16T22:46:00.123Z",
      "updated_at": "2024-11-16T22:46:00.123Z",
      "version": 1,
      "nodes": [
        {
          "nodeid": "0",
          "x": 300,
          "y": 80.671875
        },
        {
          "nodeid": "1",
          "x": 600,
          "y": 50.671875
        }
      ],
      "edges": [
        {
          "from_nodeid": "0",
          "to_nodeid": "1"
        }
      ]
    },
    {
      "graphid": 6,
      "name": "Untitled Graph",
      "userid": 6,
      "description": "Graph created via the workspace",
      "created_at": "2024-11-16T22:50:30.456Z",
      "updated_at": "2024-11-16T22:50:30.456Z",
      "version": 1,
      "nodes": [
        {
          "nodeid": "0",
          "x": 350,
          "y": 120.671875
        },
        {
          "nodeid": "1",
          "x": 650,
          "y": 60.671875
        }
      ],
      "edges": [
        {
          "from_nodeid": "0",
          "to_nodeid": "1"
        }
      ]
    },
    {
      "name": "Untitled Graph",
      "description": "Graph created via the workspace",
      "nodes": [
        {
          "nodeid": "8501f28f-4a1e-4e33-a9c4-92f5af6ff840",
          "x": 291,
          "y": 109.671875
        },
        {
          "nodeid": "8a1c883f-e255-4873-a26b-a62ee9fb5ad3",
          "x": 664,
          "y": 38.671875
        }
      ],
      "edges": [
        {
          "from_nodeid": "8501f28f-4a1e-4e33-a9c4-92f5af6ff840",
          "to_nodeid": "8a1c883f-e255-4873-a26b-a62ee9fb5ad3"
        }
      ],
      "graphid": 7,
      "created_at": "2024-11-16T22:56:22.236Z",
      "updated_at": "2024-11-16T22:56:22.236Z",
      "version": 1
    },
    {
      "name": "Untitled Graph",
      "description": "Graph created via the workspace",
      "nodes": [
        {
          "nodeid": "e5d9413f-2753-4cb6-b5f3-367a453e90da",
          "x": 391,
          "y": 102.671875
        },
        {
          "nodeid": "b18d5185-61ba-4708-a701-8d6ebf9fc832",
          "x": 850,
          "y": 67.671875
        }
      ],
      "edges": [
        {
          "from_nodeid": "e5d9413f-2753-4cb6-b5f3-367a453e90da",
          "to_nodeid": "b18d5185-61ba-4708-a701-8d6ebf9fc832"
        }
      ],
      "graphid": 8,
      "created_at": "2024-11-17T00:02:45.784Z",
      "updated_at": "2024-11-17T00:02:45.784Z",
      "version": 1
    },
    {
      "name": "Untitled Graph",
      "description": "Graph created via the workspace",
      "nodes": [
        {
          "nodeid": "d9f1f182-959b-4f8a-8326-4377aef29675",
          "x": 584,
          "y": 86.671875
        },
        {
          "nodeid": "2a9edd08-7d13-4300-9e71-3c85a3deaf01",
          "x": 838,
          "y": 57.671875
        }
      ],
      "edges": [
        {
          "from_nodeid": "d9f1f182-959b-4f8a-8326-4377aef29675",
          "to_nodeid": "2a9edd08-7d13-4300-9e71-3c85a3deaf01"
        }
      ],
      "graphid": 9,
      "created_at": "2024-11-17T00:09:33.328Z",
      "updated_at": "2024-11-17T00:09:33.328Z",
      "version": 1
    },
    {
      "name": "Untitled Graph",
      "description": "Graph created via the workspace",
      "nodes": [
        {
          "nodeid": "b532e219-54d7-430a-8a49-617e59d31964",
          "x": 552,
          "y": 109.671875
        },
        {
          "nodeid": "d997ed4c-7792-4153-901b-cd9eb505d1c1",
          "x": 893,
          "y": 30.671875
        }
      ],
      "edges": [
        {
          "from_nodeid": "b532e219-54d7-430a-8a49-617e59d31964",
          "to_nodeid": "d997ed4c-7792-4153-901b-cd9eb505d1c1"
        }
      ],
      "userid": "undefined",
      "graphid": 10,
      "created_at": "2024-11-17T00:12:48.652Z",
      "updated_at": "2024-11-17T00:12:48.652Z",
      "version": 1
    },
    {
      "name": "Untitled Graph",
      "description": "Graph created via the workspace",
      "nodes": [
        {
          "nodeid": "3fe1c19c-98c1-48ff-a35b-e81783095958",
          "x": 387,
          "y": 118.671875
        },
        {
          "nodeid": "cfc0ce58-c97f-4b35-87bc-5eff362c9ffe",
          "x": 693,
          "y": 60.671875
        }
      ],
      "edges": [
        {
          "from_nodeid": "3fe1c19c-98c1-48ff-a35b-e81783095958",
          "to_nodeid": "cfc0ce58-c97f-4b35-87bc-5eff362c9ffe"
        }
      ],
      "userid": 6,
      "graphid": 11,
      "created_at": "2024-11-17T00:36:31.865Z",
      "updated_at": "2024-11-17T00:36:31.865Z",
      "version": 1
    }
  ]
}